karan90988pdf-2.0.dist-info/licenses/license
karanpdf/__init__.py
karanpdf/pdf2text.py
karanpdf/text2pdf.py
karan90988pdf-2.0.dist-info/METADATA
karan90988pdf-2.0.dist-info/WHEEL
karan90988pdf-2.0.dist-info/top_level.txt
karan90988pdf-2.0.dist-info/RECORD
