Metadata-Version: 2.4
Name: karan90988pdf
Version: 2.0
Summary: This the homepage of our project
License-File: license
Dynamic: license-file
Dynamic: summary
